{
  "timestamp": 1764188215,
  "episode": 254,
  "checkpoint": "ppo_checkpoint_254_1764188215.pt",
  "config": {
    "LEARNING_RATE": 0.0003,
    "GAMMA": 0.92,
    "GAE_LAMBDA": 0.95,
    "PPO_EPOCHS": 4,
    "PPO_CLIP": 0.2,
    "BATCH_SIZE": 64,
    "ENTROPY_COEF": 0.01,
    "MAX_GRAD_NORM": 0.5
  },
  "stats": {
    "total_messages": 1222375,
    "total_updates": 1222375,
    "total_reward": -57983.82499841271,
    "food_counts": [
      378638,
      445713,
      398024
    ]
  },
  "recent_avg_return": -51616.23099856021
}